dltool/__init__.py
dltool/algorithm.py
dltool/log.py
dltool/train.py
dltool/types.py
dltool/utils.py
dltool/visualize.py
dltool/data/__init__.py
dltool/data/file.py
dltool/data/time.py
dltool/data/union.py
dltool/data/utils.py
dltool-1.0.1.dist-info/LICENSE
dltool-1.0.1.dist-info/METADATA
dltool-1.0.1.dist-info/WHEEL
dltool-1.0.1.dist-info/top_level.txt
dltool-1.0.1.dist-info/RECORD
