Metadata-Version: 2.1
Name: dltool
Version: 1.0.1
Summary: A small library with handy methods for DL with Pytorch
Author-email: Artem Mikhaylov <simplerick@yandex.com>
License: BSD 3-Clause License
Project-URL: Homepage, https://github.com/simplerick/dltool
Project-URL: Bug Tracker, https://github.com/simplerick/dltool/issues
Classifier: Programming Language :: Python :: 3
Classifier: Intended Audience :: Developers
Classifier: License :: OSI Approved :: BSD License
Requires-Python: >=3.10
License-File: LICENSE
Requires-Dist: torch (>=1.12)
Requires-Dist: numpy (>=1.23)
Requires-Dist: pandas (>=2.0.0)
